policyengine_us
